cam/__init__.py
cam/controller.py
cam/main.py
cam/app_tree/__init__.py
cam/app_tree/flask_app_tree.py
cam/app_tree/java_script_tree.py
cam/app_tree/js_tree/__init__.py
cam/app_tree/js_tree/templates.py
cam/app_tree/js_tree/tree.py
cam/app_tree/py_module_tree/__init__.py
cam/app_tree/py_module_tree/tree.py
cam/app_tree/templates/__init__.py
cam/app_tree/templates/javascript_template.py
cam/app_tree/templates/mit_licence.py
cam/app_tree/tree/__init__.py
cam/app_tree/tree/javascript_tree.py
cam/app_tree/tree/python_module_tree.py
cam/command/__init__.py
cam/command/commad.py
cam/command/command.py
cam/create_app/__init__.py
cam/create_app/create_app.py
cam/run/__init__.py
cam/run/run.py
cam/structure/__init__.py
cam/structure/structure.py
cam/templates/__init__.py
cam/utils/__init__.py
cam/utils/format.py
cam/utils/mit_licence.py
cam_cli_tool/__init__.py
cam_cli_tool/controller.py
cam_cli_tool/main.py
cam_cli_tool/app_tree/__init__.py
cam_cli_tool/app_tree/js_tree/__init__.py
cam_cli_tool/app_tree/js_tree/templates.py
cam_cli_tool/app_tree/js_tree/tree.py
cam_cli_tool/app_tree/py_module_tree/__init__.py
cam_cli_tool/app_tree/py_module_tree/tree.py
cam_cli_tool/command/__init__.py
cam_cli_tool/command/command.py
cam_cli_tool/create_app/__init__.py
cam_cli_tool/create_app/create_app.py
cam_cli_tool/run/__init__.py
cam_cli_tool/run/run.py
cam_cli_tool/utils/__init__.py
cam_cli_tool/utils/format.py
cam_cli_tool/utils/mit_licence.py
cam_cli_tool-0.2.15.dist-info/LICENSE.txt
cam_cli_tool-0.2.15.dist-info/METADATA
cam_cli_tool-0.2.15.dist-info/WHEEL
cam_cli_tool-0.2.15.dist-info/entry_points.txt
cam_cli_tool-0.2.15.dist-info/top_level.txt
cam_cli_tool-0.2.15.dist-info/RECORD
