Metadata-Version: 2.1
Name: cam-cli-tool
Version: 0.2.15
Summary: cam CLI is a command-line tool for creating boilerplate code for various types of applications
Home-page: https://github.com/shaileshpandit141/cam-cli-tool.git
Author: shailesh
Author-email: shaileshpandit141@gmail.com.com
Classifier: Programming Language :: Python :: 3
Classifier: License :: OSI Approved :: MIT License
Classifier: Operating System :: OS Independent
Requires-Python: >=3.8
License-File: LICENSE.txt
Requires-Dist: livereload>=2.5
